[
    {
      "name": "Panera Bread",
      "rating": 2.8,
      "distance": 4.3,
      "deliveryTime": 43,
      "cuisine": "Somali",
      "image": "panera_bread.jpg"
    },
    {
      "name": "Olive Garden",
      "rating": 1.9,
      "distance": 3.3,
      "deliveryTime": 24,
      "cuisine": "Italian",
      "image": "olive_garden.jpg"
    },
    {
      "name": "TGI Fridays",
      "rating": 1.8,
      "distance": 6.1,
      "deliveryTime": 40,
      "cuisine": "American",
      "image": "tgi_fridays.jpg"
    },
    {
      "name": "Pizza Hut",
      "rating": 3.5,
      "distance": 7.9,
      "deliveryTime": 53,
      "cuisine": "Pizza",
      "image": "pizza_hut.jpg"
    },
    {
      "name": "KFC",
      "rating": 4.1,
      "distance": 6.2,
      "deliveryTime": 3,
      "cuisine": "Fast Food",
      "image": "kfc.jpg"
    },
    {
      "name": "IHOP",
      "rating": 3.2,
      "distance": 1.6,
      "deliveryTime": 52,
      "cuisine": "American",
      "image": "ihop.jpg"
    },
    {
      "name": "Denny's",
      "rating": 4.3,
      "distance": 4.1,
      "deliveryTime": 46,
      "cuisine": "American",
      "image": "dennys.jpg"
    },
    {
      "name": "Dairy Queen",
      "rating": 0.3,
      "distance": 3.8,
      "deliveryTime": 2,
      "cuisine": "Fast Food",
      "image": "dairy_queen.jpg"
    },
    {
      "name": "Buffalo Wild Wings",
      "rating": 2.9,
      "distance": 4.7,
      "deliveryTime": 21,
      "cuisine": "American",
      "image": "buffalo_wild_wings.jpg"
    },
    {
      "name": "Taco Bell",
      "rating": 3.9,
      "distance": 8.6,
      "deliveryTime": 42,
      "cuisine": "Mexican",
      "image": "taco_bell.jpg"
    },
    {
      "name": "Red Lobster",
      "rating": 5.0,
      "distance": 1.5,
      "deliveryTime": 11,
      "cuisine": "Seafood",
      "image": "red_lobster.jpg"
    }
  ]
  